eq1/tabla1.v
//Carlos Cuellar Klingenberger #19275 UVG
//Archivo correspondiente a la SOP de la tabla 1

//Creo el módulo
module Tabla1();

//Creo las variables de entrada 
//y salidas de las diversas compuertas
reg A;
reg B;
reg C;
wire out0;
wire out1;
wire out2;
wire out3; 
wire out4;
wire out5;
wire out6;
wire out7;
wire Y;

not op0(out0, A); 
not op1(out1, B);
not op2(out2, C);

and op3(out3, out0, out1, out2);
and op4(out4, out0, B, out2);
and op5(out5, A, out1, out2);
and op6(out6, A, out1, C);
and op7(out7, A, B, C);

or op8(Y, out3, out4, out5, out6, out7);

//Inicio de las operaciones
initial begin

//Se agrega información a imprimir para facilitar comprensión
	$display("A B C | Y");
	$display("---------");

//Se especifica las variables cuyos estados
//Se desean monitorear	
	$monitor("%b %b %b | %b", A, B, C, Y);
	A = 0; B = 0; C = 0;
	#1 C = 1;
	#1 B = 1; C = 0;
	#1 C = 1;
	#1 A = 1; B = 0; C = 0;
	#1 C = 1;
	#1 B = 1; C = 0;
	#1 C = 1;
	#1 $finish;
end

//Código para habilitar GTKWave
	initial
		begin
			$dumpfile("Tabla1_tb.vcd");
			$dumpvars(0, Tabla1);
		end
endmodule

eq1/Tabla1_tb.vcd
$date
	Fri Jul 31 23:32:22 2020
$end
$version
	Icarus Verilog
$end
$timescale
	1ps
$end
$scope module Tabla1 $end
$var wire 1 ! Y $end
$var wire 1 " out0 $end
$var wire 1 # out1 $end
$var wire 1 $ out2 $end
$var wire 1 % out3 $end
$var wire 1 & out4 $end
$var wire 1 ' out5 $end
$var wire 1 ( out6 $end
$var wire 1 ) out7 $end
$var reg 1 * A $end
$var reg 1 + B $end
$var reg 1 , C $end
$upscope $end
$enddefinitions $end
#0
$dumpvars
0,
0+
0*
0)
0(
0'
0&
1%
1$
1#
1"
1!
$end
#1
0!
0%
0$
1,
#2
1!
1&
1$
0#
0,
1+
#3
0!
0&
0$
1,
#4
1!
1'
1$
1#
0"
0,
0+
1*
#5
0'
1(
0$
1,
#6
0!
0(
1$
0#
0,
1+
#7
1!
1)
0$
1,
