eq5/Tabla3.v
//Carlos Cuellar Klingenberger #19275 UVG
//Archivo correspondiente a la SOP de la tabla 3

//Creo el módulo
module Tabla3();

//Creo las variables de entrada 
//y salidas de las diversas compuertas
reg A;
reg B;
reg C;
reg D;
wire out0;
wire out1;
wire out2;
wire out3;
wire out4;
wire out5;
wire out6;
wire out7;
wire out8;
wire out9;
wire out10;
wire Y;

not op0(out0, A);
not op1(out1, B);
not op2(out2, C);
not op3(out3, D);

and op4(out4, out0, out1, out2, out3);
and op5(out5, out0, out1, out2, D);
and op6(out6, out0, out1, C, out3);
and op7(out7, out0, out1, C, D);
and op8(out8, A, out1, out2, out3);
and op9(out9, A, out1, C, out3);
and op10(out10, A, B, C, out3);

or op11(Y, out4, out5, out6, out7, out8, out9, out10);

//Inicio de las operaciones
initial begin

//Se agrega información a imprimir para facilitar comprensión
	$display("A B C D | Y");
	$display("-----------");

//Se especifican las variables cuyos estados se desean monitorear
	$monitor("%b %b %b %b | %b", A, B, C, D, Y);
	A = 0; B = 0; C = 0; D = 0;
	#1 D = 1;
	#1 D = 0; C = 1;
	#1 D = 1; 
	#1 D = 0; C = 0; B = 1;
	#1 D = 1;
	#1 D = 0; C = 1;
	#1 D = 1;
	#1 D = 0; C = 0; B = 0; A = 1;
	#1 D = 1;
	#1 D = 0; C = 1; 
	#1 D = 1; 
	#1 D = 0; C = 0; B = 1; 
	#1 D = 1;
	#1 D = 0; C = 1;
	#1 D = 1;
end

//Código para habilitar GTKWave
	initial
		begin 
		$dumpfile ("Tabla3_tb.vcd");
		$dumpvars(0, Tabla3);
	end
endmodule

eq5/dump.vcd
$date
	Fri Jul 31 19:49:48 2020
$end
$version
	Icarus Verilog
$end
$timescale
	1ps
$end
$scope module Tabla3 $end
$var wire 1 ! Y $end
$var wire 1 " out0 $end
$var wire 1 # out1 $end
$var wire 1 $ out10 $end
$var wire 1 % out2 $end
$var wire 1 & out3 $end
$var wire 1 ' out4 $end
$var wire 1 ( out5 $end
$var wire 1 ) out6 $end
$var wire 1 * out7 $end
$var wire 1 + out8 $end
$var wire 1 , out9 $end
$var reg 1 - A $end
$var reg 1 . B $end
$var reg 1 / C $end
$var reg 1 0 D $end
$upscope $end
$enddefinitions $end
#0
$dumpvars
00
0/
0.
0-
0,
0+
0*
0)
0(
1'
1&
1%
0$
1#
1"
1!
$end
#1
0'
1(
0&
10
#2
1)
0%
0(
1&
1/
00
#3
0)
1*
0&
10
#4
0!
0#
1%
0*
1&
1.
0/
00
#5
0&
10
#6
0%
1&
1/
00
#7
0&
10
#8
1!
1+
0"
1#
1%
1&
1-
0.
0/
00
#9
0!
0+
0&
10
#10
1!
1,
0%
1&
1/
00
#11
0!
0,
0&
10
#12
0#
1%
1&
1.
0/
00
#13
0&
10
#14
1!
1$
0%
1&
1/
00
#15
0!
0$
0&
10
